sg/__init__.py
sg/main.py
db_generator-1.0.4.dist-info/METADATA
db_generator-1.0.4.dist-info/WHEEL
db_generator-1.0.4.dist-info/top_level.txt
db_generator-1.0.4.dist-info/RECORD
