Metadata-Version: 2.1
Name: db-generator
Version: 1.0.4
Summary: A package which will create sqlite3 database code by configuring them in json file
Author: Ganesh Yatesh Joshi
Author-email: ganesh.22110724@viit.ac.in
Keywords: python,database,json configuration for database,json,sqlite3,mobile database
Classifier: Development Status :: 1 - Planning
Classifier: Intended Audience :: Developers
Classifier: Programming Language :: Python :: 3
Classifier: Operating System :: Unix
Classifier: Operating System :: MacOS :: MacOS X
Classifier: Operating System :: Microsoft :: Windows
